gren/__init__.py
gren/config.py
gren/errors.py
gren/adapters/__init__.py
gren/adapters/submitit.py
gren/core/__init__.py
gren/core/gren.py
gren/core/list.py
gren/dashboard/__init__.py
gren/dashboard/__main__.py
gren/dashboard/main.py
gren/dashboard/scanner.py
gren/dashboard/api/__init__.py
gren/dashboard/api/models.py
gren/dashboard/api/routes.py
gren/dashboard/frontend/dist/favicon.svg
gren/dashboard/frontend/dist/index.html
gren/dashboard/frontend/dist/assets/index--bTy2zC5.css
gren/dashboard/frontend/dist/assets/index-DqQ_HmBH.js
gren/runtime/__init__.py
gren/runtime/env.py
gren/runtime/logging.py
gren/runtime/tracebacks.py
gren/serialization/__init__.py
gren/serialization/serializer.py
gren/storage/__init__.py
gren/storage/metadata.py
gren/storage/state.py
gren-0.2.0.dist-info/METADATA
gren-0.2.0.dist-info/WHEEL
gren-0.2.0.dist-info/entry_points.txt
gren-0.2.0.dist-info/RECORD
