Metadata-Version: 2.4
Name: gren
Version: 0.2.0
Summary: Cacheable, nested pipelines for Python. Define computations as configs; gren handles caching, state tracking, and result reuse across runs.
Author-email: Herman Brunborg <herman@brunborg.com>
Requires-Python: >=3.12
Requires-Dist: chz>=0.4.0
Requires-Dist: cloudpickle>=3.1.1
Requires-Dist: pydantic>=2.12.5
Requires-Dist: python-dotenv>=1.0.0
Requires-Dist: rich>=14.2.0
Requires-Dist: submitit>=1.5.3
Provides-Extra: dashboard
Requires-Dist: fastapi>=0.109.0; extra == 'dashboard'
Requires-Dist: typer>=0.9.0; extra == 'dashboard'
Requires-Dist: uvicorn[standard]>=0.27.0; extra == 'dashboard'
